SherLocking/__init__.py
SherLocking/__main__.py
SherLocking/activation.py
SherLocking/config.py
SherLocking/file.py
SherLocking/main.py
SherLocking-0.0.6.dist-info/LICENSE
SherLocking-0.0.6.dist-info/METADATA
SherLocking-0.0.6.dist-info/WHEEL
SherLocking-0.0.6.dist-info/top_level.txt
SherLocking-0.0.6.dist-info/RECORD
