Metadata-Version: 2.1
Name: SherLocking
Version: 0.0.6
Summary: Applies activation for any program.
Author: Armando Chaparro
Author-email: <pylejandria@gmail.com>
Keywords: python,locking,activation,trial,license
Classifier: Development Status :: 1 - Planning
Classifier: Intended Audience :: Developers
Classifier: Programming Language :: Python :: 3
Classifier: Operating System :: Microsoft :: Windows
License-File: LICENSE
Requires-Dist: ttkbootstrap
